pyshutdown/__init__.py
pyshutdown/myfunctions.py
pyshutdown-2.0.dist-info/METADATA
pyshutdown-2.0.dist-info/WHEEL
pyshutdown-2.0.dist-info/top_level.txt
pyshutdown-2.0.dist-info/RECORD
