Metadata-Version: 2.1
Name: pyshutdown
Version: 2.0
Summary: A library to shut down, reboot, etc. in Python.
Home-page: UNKNOWN
Author: Gabriel Bourneau
License: GNU GPLv3
Platform: UNKNOWN
